data_structures/__init__.py
data_structures/array.py
data_structures/graph.py
data_structures/linked_list.py
data_structures/queue.py
data_structures/stack.py
data_structures/tree.py
laity_data_structures-0.1.5.dist-info/licenses/LICENSE
laity_data_structures-0.1.5.dist-info/METADATA
laity_data_structures-0.1.5.dist-info/WHEEL
laity_data_structures-0.1.5.dist-info/top_level.txt
laity_data_structures-0.1.5.dist-info/RECORD
