Metadata-Version: 2.4
Name: laity_data_structures
Version: 0.1.5
Summary: Data Structure Package By Pappalaity
Home-page: https://github.com/PappaLaity/pappa-laity-data-structures-python
Author: Pappa laity
Author-email: pappalaity@gmail.com
Classifier: Programming Language :: Python :: 3
Classifier: License :: OSI Approved :: MIT License
Classifier: Operating System :: OS Independent
Requires-Python: >=3.12
License-File: LICENSE
Dynamic: author
Dynamic: author-email
Dynamic: classifier
Dynamic: description
Dynamic: description-content-type
Dynamic: home-page
Dynamic: license-file
Dynamic: requires-python
Dynamic: summary
